setup.py
FaBoLCD_PCF8574/PCF8574.py
FaBoLCD_PCF8574/__init__.py
FaBoLCD_PCF8574.egg-info/PKG-INFO
FaBoLCD_PCF8574.egg-info/SOURCES.txt
FaBoLCD_PCF8574.egg-info/dependency_links.txt
FaBoLCD_PCF8574.egg-info/top_level.txt